izbushka/__init__.py
izbushka/__main__.py
izbushka/cli.py
izbushka/entities.py
izbushka/errors.py
izbushka/history_repo.py
izbushka/migrations_repo.py
izbushka/migrations_service.py
izbushka/operations.py
izbushka/protocols.py
izbushka/sql.py
izbushka-0.2.3.dist-info/LICENSE
izbushka-0.2.3.dist-info/WHEEL
izbushka-0.2.3.dist-info/METADATA
izbushka-0.2.3.dist-info/RECORD
