Metadata-Version: 2.1
Name: izbushka
Version: 0.2.3
Summary: 
Author: Anton Evdokimov
Author-email: meowmeowcode@gmail.com
Requires-Python: >=3.9
Classifier: Programming Language :: Python :: 3
Classifier: Programming Language :: Python :: 3.10
Classifier: Programming Language :: Python :: 3.9
Requires-Dist: PyPika (>=0.48.9,<0.49.0)
Requires-Dist: PyYAML (<6)
Requires-Dist: click (>=8.1.3,<9.0.0)
Requires-Dist: clickhouse-connect (>=0.4.1,<0.5.0)
Requires-Dist: natsort (>=8.2.0,<9.0.0)
